basix/__init__.py
basix/_basixcpp.cp310-win_amd64.pyd
basix/_basixcpp.pyi
basix/basix.dll
basix/cell.py
basix/finite_element.py
basix/include/basix/cell.h
basix/include/basix/dof-transformations.h
basix/include/basix/e-brezzi-douglas-marini.h
basix/include/basix/e-bubble.h
basix/include/basix/e-crouzeix-raviart.h
basix/include/basix/e-hermite.h
basix/include/basix/e-hhj.h
basix/include/basix/e-lagrange.h
basix/include/basix/e-nce-rtc.h
basix/include/basix/e-nedelec.h
basix/include/basix/e-raviart-thomas.h
basix/include/basix/e-regge.h
basix/include/basix/e-serendipity.h
basix/include/basix/element-families.h
basix/include/basix/finite-element.h
basix/include/basix/indexing.h
basix/include/basix/interpolation.h
basix/include/basix/lattice.h
basix/include/basix/maps.h
basix/include/basix/math.h
basix/include/basix/mdspan.hpp
basix/include/basix/moments.h
basix/include/basix/polynomials.h
basix/include/basix/polyset.h
basix/include/basix/precompute.h
basix/include/basix/quadrature.h
basix/include/basix/sobolev-spaces.h
basix/include/basix/types.h
basix/include/basix/version.h
basix/include/finite-element.h
basix/interpolation.py
basix/lattice.py
basix/libgcc_s_seh-1.dll
basix/libgfortran-5.dll
basix/liblapack.dll
basix/libquadmath-0.dll
basix/libwinpthread-1.dll
basix/maps.py
basix/numba_helpers.py
basix/openblas.dll
basix/polynomials.py
basix/py.typed
basix/quadrature.py
basix/sobolev_spaces.py
basix/ufl.py
basix/utils.py
lib/basix.lib
lib/cmake/basix/BasixConfig.cmake
lib/cmake/basix/BasixConfigVersion.cmake
lib/cmake/basix/BasixTargets-release.cmake
lib/cmake/basix/BasixTargets.cmake
fenics_basix-0.10.0.dist-info/METADATA
fenics_basix-0.10.0.dist-info/WHEEL
fenics_basix-0.10.0.dist-info/licenses/LICENSE
fenics_basix-0.10.0.dist-info/RECORD
