Metadata-Version: 2.2
Name: fenics-basix
Version: 0.10.0
Summary: Basix Python interface
Author: FEniCS Steering Council
Author-Email: Unknown <fenics-steering-council@googlegroups.com>
License: MIT License
Project-URL: homepage, https://fenicsproject.org
Project-URL: repository, https://github.com/fenics/basix.git
Project-URL: documentation, https://docs.fenicsproject.org
Requires-Python: >=3.10
Requires-Dist: numpy>=1.21
Provides-Extra: docs
Requires-Dist: markdown; extra == "docs"
Requires-Dist: pylit3; extra == "docs"
Requires-Dist: pyyaml; extra == "docs"
Requires-Dist: sphinx; extra == "docs"
Requires-Dist: sphinx_rtd_theme; extra == "docs"
Provides-Extra: lint
Requires-Dist: ruff; extra == "lint"
Provides-Extra: optional
Requires-Dist: numba; extra == "optional"
Requires-Dist: fenics-ufl<2025.3.0,>=2025.2.0; extra == "optional"
Provides-Extra: test
Requires-Dist: pytest; extra == "test"
Requires-Dist: sympy; extra == "test"
Requires-Dist: scipy; extra == "test"
Requires-Dist: matplotlib; extra == "test"
Requires-Dist: fenics-basix[optional]; extra == "test"
Provides-Extra: ci
Requires-Dist: mypy; extra == "ci"
Requires-Dist: pytest-xdist; extra == "ci"
Requires-Dist: fenics-basix[docs,lint,optional,test]; extra == "ci"
